pyte/__init__.py
pyte/__main__.py
pyte/charsets.py
pyte/compat.py
pyte/control.py
pyte/escape.py
pyte/graphics.py
pyte/modes.py
pyte/screens.py
pyte/streams.py
pyte-0.8.0.dist-info/AUTHORS
pyte-0.8.0.dist-info/LICENSE
pyte-0.8.0.dist-info/METADATA
pyte-0.8.0.dist-info/WHEEL
pyte-0.8.0.dist-info/top_level.txt
pyte-0.8.0.dist-info/RECORD
