Metadata-Version: 2.1
Name: pyte
Version: 0.8.0
Summary: Simple VTXXX-compatible terminal emulator.
Home-page: https://github.com/selectel/pyte
Author: Sergei Lebedev
Author-email: superbobry@gmail.com
License: UNKNOWN
Keywords: vt102,vte,terminal emulator
Platform: any
Classifier: Development Status :: 5 - Production/Stable
Classifier: Environment :: Console
Classifier: Intended Audience :: Developers
Classifier: Operating System :: OS Independent
Classifier: License :: OSI Approved :: GNU Lesser General Public License v3 (LGPLv3)
Classifier: Programming Language :: Python :: 2.6
Classifier: Programming Language :: Python :: 2.7
Classifier: Programming Language :: Python :: 3.5
Classifier: Programming Language :: Python :: 3.6
Classifier: Topic :: Terminals :: Terminal Emulators/X Terminals
License-File: LICENSE
License-File: AUTHORS
Requires-Dist: wcwidth
